Metadata-Version: 2.1
Name: poetry-demo
Version: 0.1.1
Summary: 
Author: Shabie Iqbal
Author-email: shabieiqbal@gmail.com
Requires-Python: >=2.7,<3.0
Classifier: Programming Language :: Python :: 2
Classifier: Programming Language :: Python :: 2.7
Requires-Dist: pendulum (>=2.0.5,<3.0.0)
